MANIFEST.in
README.rst
setup.py
developer_toolkit/__init__.py
developer_toolkit/forms.py
developer_toolkit/urls.py
developer_toolkit/views.py
developer_toolkit/templates/admin/index.html
developer_toolkit/templates/developer_toolkit/mail_form.html
django_developer_toolkit.egg-info/PKG-INFO
django_developer_toolkit.egg-info/SOURCES.txt
django_developer_toolkit.egg-info/dependency_links.txt
django_developer_toolkit.egg-info/requires.txt
django_developer_toolkit.egg-info/top_level.txt