Metadata-Version: 1.1
Name: django-developer-toolkit
Version: 0.3.0
Summary: Django utility app for Django developers.
Home-page: https://github.com/PragmaticMates/django-developer-toolkit
Author: Pragmatic Mates
Author-email: info@pragmaticmates.com
License: GPL License
Keywords: django toolkit developer utility
Platform: UNKNOWN
Classifier: Programming Language :: Python
Classifier: Programming Language :: Python :: 2.5
Classifier: Programming Language :: Python :: 2.6
Classifier: Programming Language :: Python :: 2.7
Classifier: Operating System :: OS Independent
Classifier: Environment :: Web Environment
Classifier: Intended Audience :: Developers
Classifier: Framework :: Django
Classifier: License :: OSI Approved :: BSD License
Classifier: Development Status :: 3 - Alpha
